[{"bPigeonID":"adr","bPigeonName":"fadsfsd","bPigeonYear":"2020","bPigeonColour":"sd","bPigeonGender":"C","bPigeonLetters":"sad","bGeneticCode1":"b","bGeneticCode2":"","bGeneticCode3":"","bGeneticCode4":""},{"bPigeonID":"gcf","bPigeonName":"td","bPigeonYear":"2021","bPigeonColour":"gcj","bPigeonGender":"C","bPigeonLetters":"hx","bGeneticCode1":"dgr","bGeneticCode2":"","bGeneticCode3":"","bGeneticCode4":""},{"bPigeonID":"htfx","bPigeonName":"hfx","bPigeonYear":"2022","bPigeonColour":"jhv","bPigeonGender":"C","bPigeonLetters":"dg","bGeneticCode1":"o","bGeneticCode2":"","bGeneticCode3":"","bGeneticCode4":""},{"bPigeonID":"123","bPigeonName":"sfd","bPigeonYear":"2022","bPigeonColour":"asd","bPigeonGender":"C","bPigeonLetters":"bsfd","bGeneticCode1":"b","bGeneticCode2":"b","bGeneticCode3":"b","bGeneticCode4":"b"}]